agent_playbook/__init__.py
agent_playbook/_export/export_agent.py
agent_playbook/_export/export_types.py
agent_playbook/agent_loader.py
agent_playbook/api.py
agent_playbook/cli.py
agent_playbook/py.typed
agent_playbook/server.py
agent_playbook/static/assets/index-Bem6lZ_N.js
agent_playbook/static/assets/index-Bi_99665.css
agent_playbook/static/favicon.ico
agent_playbook/static/index.html
agent_playbook/types.py
agent_playbook-0.1.3.dist-info/METADATA
agent_playbook-0.1.3.dist-info/WHEEL
agent_playbook-0.1.3.dist-info/entry_points.txt
agent_playbook-0.1.3.dist-info/licenses/LICENSE
agent_playbook-0.1.3.dist-info/RECORD
