Metadata-Version: 2.4
Name: agent-playbook
Version: 0.1.3
Summary: The Storybook for AI Agents
License-File: LICENSE
Author: Or Levi
Author-email: orlevi128@gmail.com
Requires-Python: >=3.10,<4.0
Classifier: Programming Language :: Python :: 3
Classifier: Programming Language :: Python :: 3.10
Classifier: Programming Language :: Python :: 3.11
Classifier: Programming Language :: Python :: 3.12
Classifier: Programming Language :: Python :: 3.13
Classifier: Programming Language :: Python :: 3.14
Requires-Dist: clantic (>=0.2.0,<0.3.0)
Requires-Dist: dacite (>=1.9.2,<2.0.0)
Requires-Dist: fastapi (>=0.100.0,<1.0.0)
Requires-Dist: httpx (>=0.28.1)
Requires-Dist: pydantic-ai-slim (>=1.7.0,<2.0.0)
Requires-Dist: uvicorn (>=0.31.1)
Project-URL: Homepage, https://github.com/orlevii/agent-playbook
Project-URL: Repository, https://github.com/orlevii/agent-playbook
